pymdvar/__init__.py
pymdvar/py.typed
pymdvar/pymdvar.py
pymdvar-1.0.3.dist-info/AUTHORS
pymdvar-1.0.3.dist-info/LICENSE
pymdvar-1.0.3.dist-info/METADATA
pymdvar-1.0.3.dist-info/WHEEL
pymdvar-1.0.3.dist-info/pbr.json
pymdvar-1.0.3.dist-info/top_level.txt
pymdvar-1.0.3.dist-info/RECORD
