Metadata-Version: 2.1
Name: pymdvar
Version: 1.0.3
Summary: Python-Markdown extension for key-value pair conversion
Home-page: https://github.com/luevano/pymdvar
Author: David Luevano Alvarado
Author-email: david@luevano.xyz
License: GPLv3
Keywords: python,extension,plugin,markdown,website
Classifier: License :: OSI Approved :: GNU General Public License v3 (GPLv3)
Classifier: Operating System :: OS Independent
Classifier: Programming Language :: Python
Classifier: Programming Language :: Python :: 3
Classifier: Programming Language :: Python :: 3.7
Classifier: Programming Language :: Python :: 3.8
Classifier: Programming Language :: Python :: 3.9
Classifier: Programming Language :: Python :: 3.10
Classifier: Programming Language :: Python :: 3.11
Classifier: Programming Language :: Python :: 3 :: Only
Classifier: Topic :: Communications :: Email :: Filters
Classifier: Topic :: Internet :: WWW/HTTP :: Dynamic Content :: CGI Tools/Libraries
Classifier: Topic :: Internet :: WWW/HTTP :: Site Management
Classifier: Topic :: Software Development :: Documentation
Classifier: Topic :: Software Development :: Libraries :: Python Modules
Classifier: Topic :: Text Processing :: Filters
Classifier: Topic :: Text Processing :: Markup :: HTML
Classifier: Topic :: Text Processing :: Markup :: Markdown
License-File: LICENSE
License-File: AUTHORS
Requires-Dist: Markdown (>=3.4.1)
